setup.cfg
setup.py
hem/__init__.py
hem/config.py
hem/db.py
hem/interfaces.py
hem/schemas.py
hem/text.py
hem.egg-info/PKG-INFO
hem.egg-info/SOURCES.txt
hem.egg-info/dependency_links.txt
hem.egg-info/not-zip-safe
hem.egg-info/requires.txt
hem.egg-info/top_level.txt