Metadata-Version: 1.1
Name: hem
Version: 0.4.0
Summary: Generic utilities to help build frameworks on top of pyramid
Home-page: https://github.com/eventray/hem
Author: John Anderson
Author-email: sontek@gmail.com
License: BSD
Keywords: p,y,r,a,m,i,d
Platform: UNKNOWN
Classifier: Intended Audience :: Developers
Classifier: License :: OSI Approved :: BSD License
Classifier: Operating System :: OS Independent
Classifier: Programming Language :: Python
Classifier: Programming Language :: Python :: 3
Classifier: Topic :: Internet :: WWW/HTTP :: Dynamic Content
Classifier: Topic :: Software Development :: Libraries :: Python Modules
